diff4html/__init__.py
diff4html/diff.py
diff4html/html.py
diff4html-0.1.dist-info/METADATA
diff4html-0.1.dist-info/WHEEL
diff4html-0.1.dist-info/top_level.txt
diff4html-0.1.dist-info/RECORD
