Metadata-Version: 2.4
Name: diff4html
Version: 0.1
Summary: Tools for converting HTMLs to dicts & calculating diff between them
Home-page: https://github.com/dsp-shp/diff4html
Author: Ivan Derkach
Author-email: dsp_shp@icloud.com
License: MIT
Project-URL: Source Code, https://github.com/dsp-shp/diff4html
Classifier: Intended Audience :: Developers
Classifier: Intended Audience :: Science/Research
Classifier: License :: OSI Approved :: MIT License
Classifier: Operating System :: OS Independent
Classifier: Programming Language :: Python :: 3 :: Only
Requires-Python: >=3.11
Requires-Dist: lxml==5.3.1
Provides-Extra: dev
Requires-Dist: mypy; extra == "dev"
Requires-Dist: pylint; extra == "dev"
Requires-Dist: pytest; extra == "dev"
Requires-Dist: notebook; extra == "dev"
Dynamic: author
Dynamic: author-email
Dynamic: classifier
Dynamic: description
Dynamic: description-content-type
Dynamic: home-page
Dynamic: license
Dynamic: project-url
Dynamic: provides-extra
Dynamic: requires-dist
Dynamic: requires-python
Dynamic: summary
